{
  "schema_version": "0.2",
  "sop_id": "f002_w002_garment_bagging",
  "fps": 2.0,
  "n_frames": 40,
  "annotated_at": "2026-07-12T10:12:25+00:00",
  "events": {
    "pick_garment_from_stack": [
      {
        "start_idx": 0,
        "end_idx": 2
      }
    ],
    "insert_garment_into_bag": [
      {
        "start_idx": 11,
        "end_idx": 25
      }
    ],
    "seal_bag_flap": [
      {
        "start_idx": 21,
        "end_idx": 25
      }
    ],
    "place_package_right": [
      {
        "start_idx": 36,
        "end_idx": 38
      }
    ]
  }
}
